veetility/__init__.py
veetility/amazonads_api.py
veetility/cleaning_functions.py
veetility/email_functions.py
veetility/generic_functions.py
veetility/linkedin_api.py
veetility/matched_qa.py
veetility/point_to_point_regressor.py
veetility/quality_assessments.py
veetility/rivaliq_functions.py
veetility/s3_bucket.py
veetility/snowflake.py
veetility/tiktok_vtr.py
veetility/utility_functions.py
veetility/v_lift.py
veetility/vee_mails.py
veetility/view_through_rate.py
veetility-0.5.3.dist-info/METADATA
veetility-0.5.3.dist-info/WHEEL
veetility-0.5.3.dist-info/top_level.txt
veetility-0.5.3.dist-info/RECORD
