Metadata-Version: 2.1
Name: veetility
Version: 0.5.3
Summary: Demo library
Home-page: 
Author: Vaynermedia
Author-email: will.butler@vaynermedia.com
License: MIT
Classifier: Intended Audience :: Developers
Classifier: License :: OSI Approved :: MIT License
Classifier: Programming Language :: Python
Classifier: Programming Language :: Python :: 3
Classifier: Programming Language :: Python :: 3.6
Classifier: Programming Language :: Python :: 3.7
Classifier: Programming Language :: Python :: 3.8
Classifier: Programming Language :: Python :: 3.9
Classifier: Operating System :: OS Independent
Requires-Dist: fuzzywuzzy
Requires-Dist: gspread
Requires-Dist: gspread-dataframe
Requires-Dist: numpy
Requires-Dist: pandas
Requires-Dist: psycopg2-binary
Requires-Dist: regex
Requires-Dist: requests
Requires-Dist: SQLAlchemy (>=1.1.18)
Requires-Dist: tqdm
